MANIFEST.in
README.txt
setup.cfg
setup.py
collective/__init__.py
collective.dexteritypaste.egg-info/PKG-INFO
collective.dexteritypaste.egg-info/SOURCES.txt
collective.dexteritypaste.egg-info/dependency_links.txt
collective.dexteritypaste.egg-info/entry_points.txt
collective.dexteritypaste.egg-info/namespace_packages.txt
collective.dexteritypaste.egg-info/not-zip-safe
collective.dexteritypaste.egg-info/requires.txt
collective.dexteritypaste.egg-info/top_level.txt
collective/dexteritypaste/__init__.py
collective/dexteritypaste/dexterity.py
collective/dexteritypaste/localcommands/__init__.py
collective/dexteritypaste/localcommands/dexterity.py
collective/dexteritypaste/localcommands/templates/dexterity/behavior/behavior/+behavior_filename+.py_tmpl
collective/dexteritypaste/localcommands/templates/dexterity/behavior/behavior/configure.zcml_insert
collective/dexteritypaste/localcommands/templates/dexterity/content/content/+content_class_filename+.py_tmpl
collective/dexteritypaste/localcommands/templates/dexterity/content/profiles/default/types.xml_insert
collective/dexteritypaste/localcommands/templates/dexterity/content/profiles/default/types/+types_xml_filename+.xml_tmpl
collective/dexteritypaste/localcommands/templates/dexterity/view/browser/+view_filename+.py_tmpl
collective/dexteritypaste/localcommands/templates/dexterity/view/browser/+view_filename+_templates/view.pt
collective/dexteritypaste/templates/dexterity/setup.py_tmpl
collective/dexteritypaste/templates/dexterity/+namespace_package+/+package+/__init__.py_tmpl
collective/dexteritypaste/templates/dexterity/+namespace_package+/+package+/configure.zcml_tmpl
collective/dexteritypaste/templates/dexterity/+namespace_package+/+package+/tests.py_tmpl
collective/dexteritypaste/templates/dexterity/+namespace_package+/+package+/behavior/__init__.py
collective/dexteritypaste/templates/dexterity/+namespace_package+/+package+/behavior/configure.zcml_tmpl
collective/dexteritypaste/templates/dexterity/+namespace_package+/+package+/browser/__init__.py
collective/dexteritypaste/templates/dexterity/+namespace_package+/+package+/content/__init__.py
collective/dexteritypaste/templates/dexterity/+namespace_package+/+package+/content/configure.zcml_tmpl
collective/dexteritypaste/templates/dexterity/+namespace_package+/+package+/profiles/default/metadata.xml_tmpl
