Metadata-Version: 1.0
Name: collective.dexteritypaste
Version: 1.0alpha1
Summary: Paster templates for dexterity
Home-page: http://svn.plone.org/svn/collective/collective.dexteritypaste
Author: Izhar Firdaus
Author-email: izhar@inigo-tech.com
License: GPL
Keywords: plone dexterity
Platform: UNKNOWN
Classifier: Programming Language :: Python
Classifier: Framework :: Plone
Classifier: Framework :: Zope3
Classifier: Topic :: Software Development :: Libraries :: Python Modules
